wuwaimagen/__init__.py
wuwaimagen/client.py
wuwaimagen/src/assets/font/font_hsr.ttf
wuwaimagen/src/components/business_card.py
wuwaimagen/src/components/convene.py
wuwaimagen/src/components/event.py
wuwaimagen/src/components/main.py
wuwaimagen/src/components/material.py
wuwaimagen/src/components/wiki.py
wuwaimagen/src/generator/business_card.py
wuwaimagen/src/generator/convene.py
wuwaimagen/src/generator/event.py
wuwaimagen/src/generator/material_character.py
wuwaimagen/src/generator/material_weapon.py
wuwaimagen/src/generator/wiki.py
wuwaimagen/src/model/__init__.py
wuwaimagen/src/model/business_card.py
wuwaimagen/src/model/convene.py
wuwaimagen/src/model/event.py
wuwaimagen/src/model/material.py
wuwaimagen/src/model/wiki.py
wuwaimagen/src/settings/convene.py
wuwaimagen/src/settings/other.py
wuwaimagen/src/tools/color.py
wuwaimagen/src/tools/git.py
wuwaimagen/src/tools/http.py
wuwaimagen/src/tools/json_data.py
wuwaimagen/src/tools/pill.py
wuwaimagen/src/tools/utils.py
wuwaimagen-0.1.3.dist-info/METADATA
wuwaimagen-0.1.3.dist-info/WHEEL
wuwaimagen-0.1.3.dist-info/RECORD
