Metadata-Version: 2.1
Name: wuwaimagen
Version: 0.1.3
Summary: WuWaImaGen - is a Python module that allows you to generate images for projects based on the game Wuthering Waves
Home-page: https://github.com/Wuthery/WuWaConvene.py
License: MIT
Keywords: Wuthering,Waves,generation,WuWa,gacha,convene,card,api
Author: DeviantUa
Author-email: deviantapi@gmail.com
Requires-Python: >=3.9
Classifier: License :: OSI Approved :: MIT License
Classifier: Programming Language :: Python :: 3
Classifier: Programming Language :: Python :: 3.9
Classifier: Programming Language :: Python :: 3.10
Classifier: Programming Language :: Python :: 3.11
Requires-Dist: Pillow
Requires-Dist: aiofiles
Requires-Dist: aiohttp
Requires-Dist: anyio
Requires-Dist: beautifulsoup4
Requires-Dist: cachetools
Requires-Dist: kuro.py
Requires-Dist: more-itertools
Requires-Dist: numpy
Requires-Dist: pydantic
Project-URL: Repository, https://github.com/Wuthery/WuWaConvene.py
